{"id":"bf1931f2-ec1a-4c89-8b58-febf93ef49ba","timestamp":1759126702163,"matcher":{"static":{},"wildcard":{},"dynamic":{}},"prerendered":["/","/buildings_json","/architects_index","/cities_index","/buildings_index","/buildings_json/1","/buildings_json/2","/buildings_json/4","/buildings_json/7","/buildings_json/3","/buildings_json/5","/buildings_json/9","/buildings_json/12","/buildings_json/6","/buildings_json/11","/buildings_json/8","/buildings_json/10","/buildings-md/burj-khalifa","/cities-md/city_06","/cities-md/city_10","/cities-md/city_07","/cities-md/city_11","/cities-md/city_05","/cities-md/city_09","/cities-md/city_08","/cities-md/city_01","/buildings-md/merdeka-118","/cities-md/city_04","/cities-md/city_03","/buildings-md/shanghai-tower","/cities-md/city_02","/buildings-md/ping-an-finance-center","/buildings-md/tianjin-ctf-finance-centre","/buildings-md/one-world-trade-center","/buildings-md/lotte-world-tower","/buildings-md/guangzhou-ctf-finance-centre","/buildings-md/citic-tower","/buildings-md/shanghai-world-financial-center","/buildings-md/taipei-101","/buildings-md/makkah-royal-clock-tower","/architects-md/arq_06","/architects-md/arq_03","/architects-md/arq_02","/architects-md/arq_04","/architects-md/arq_05","/architects-md/arq_01"]}